datarobot_ts_helpers/__init__.py
datarobot_ts_helpers/ts_calendar.py
datarobot_ts_helpers/ts_clustering.py
datarobot_ts_helpers/ts_data_preparation.py
datarobot_ts_helpers/ts_data_quality.py
datarobot_ts_helpers/ts_helpers.py
datarobot_ts_helpers/ts_metrics.py
datarobot_ts_helpers/ts_modeling.py
datarobot_ts_helpers/ts_pre_processing.py
datarobot_ts_helpers/ts_predictions.py
datarobot_ts_helpers/ts_projects.py
datarobot_ts_helpers-0.1.5.dist-info/LICENSE.txt
datarobot_ts_helpers-0.1.5.dist-info/METADATA
datarobot_ts_helpers-0.1.5.dist-info/WHEEL
datarobot_ts_helpers-0.1.5.dist-info/top_level.txt
datarobot_ts_helpers-0.1.5.dist-info/RECORD
