Metadata-Version: 2.1
Name: datarobot-ts-helpers
Version: 0.1.5
Summary: A package with helper scripts for complex DataRobot AutoTS use cases
Home-page: https://github.com/jarredbultema/ts_helpers_package
Author: Jarred Bultema
Author-email: jarred.bultema@datarobot.com
License: UNKNOWN
Platform: UNKNOWN
Classifier: Programming Language :: Python :: 3
Classifier: License :: OSI Approved :: MIT License
Classifier: Operating System :: OS Independent
Requires-Python: >=3.4
Requires-Dist: setuptools (>=40.3.0)
Requires-Dist: datarobot (>=2.0)
Requires-Dist: statsmodels (>=0.9)
Requires-Dist: plotly (>=4.10)
Requires-Dist: umap-learn (>=0.3.10)
Requires-Dist: ipywidgets (>=7.5)
Requires-Dist: scikit-learn (>=0.22.1)
Requires-Dist: matplotlib (>=2.2)
Requires-Dist: seaborn (>=0.9)
Requires-Dist: xlrd (>=1.0)
Requires-Dist: tqdm (>=4.0)
